{
    "map_services": {
        "SERVICES": [
            "TCP-4500"
        ]
    },
    "map_groups": {
        "GROUPS": [
            "TF-EU1-HOST-eu1srlpm1eascno",
            "TF-EU1-HOST-eu1d138lpmlptnp2",
            "TF-EU1-HOST-eu1srlpm1ecno2",
            "TF-EU1-HOST-eu1srlpm1epno2",
            "TF-EU1-HOST-eu1srlpm1easpno",
            "TF-EU1-HOST-eu1d138lpmlptnp1"
        ]
    },
    "map_policies": {
        "TF-DRES138": {
            "category": "Application",
            "rules": {
                "6771": {
                    "display_name": "TF-6771-Netcool-Omnibus",
                    "disabled": false,
                    "source_groups": [
                        "TF-EU1-HOST-eu1d138lpmlptnp1",
                        "TF-EU1-HOST-eu1d138lpmlptnp2"
                    ],
                    "source_ips": [],
                    "destination_groups": [
                        "TF-EU1-HOST-eu1srlpm1easpno",
                        "TF-EU1-HOST-eu1srlpm1eascno",
                        "TF-EU1-HOST-eu1srlpm1ecno2",
                        "TF-EU1-HOST-eu1srlpm1epno2"
                    ],
                    "destination_ips": [],
                    "services": [
                        "TCP-4500"
                    ],
                    "action": "ALLOW",
                    "direction": "IN_OUT",
                    "logged": true,
                    "notes": "SR50973050\nSR51019758\nSR51064482",
                    "scope": [
                        "TF-EU1-HOST-eu1srlpm1eascno",
                        "TF-EU1-HOST-eu1d138lpmlptnp2",
                        "TF-EU1-HOST-eu1srlpm1ecno2",
                        "TF-EU1-HOST-eu1srlpm1epno2",
                        "TF-EU1-HOST-eu1srlpm1easpno",
                        "TF-EU1-HOST-eu1d138lpmlptnp1"
                    ]
                }
            }
        }
    }
}